{"search_parameters": {"engine": "google", "id": "c585c1cc-dad5-4d21-9605-83691286359d", "sub_id": 0, "requested_time": "2022-05-12T01:09:10.121Z", "q": "stir-fried", "location": "South Korea", "gl": "kr", "hl": "ko", "num": 20, "query_string": "q=stir-fried&hl=ko&gl=kr&uule=w+CAIQICILU291dGggS29yZWE&num=20&sourceid=chrome&ie=UTF-8&pws=0", "html_url": "http://node0011.k8s.prod.ascentlab.io:8080/serpapi/serpdata/intent/220512/2205121009/211189154105-68B2859E0BD44278A26F3D8C2DF4F7C0-00.html", "json_url": "http://node0011.k8s.prod.ascentlab.io:8080/serpapi/serpdata/intent/220512/2205121009/211189154105-68B2859E0BD44278A26F3D8C2DF4F7C0-00.json", "crawl_start_time": "2022-05-12T01:09:10.144Z", "crawl_end_time": "2022-05-12T01:09:14.233Z", "device": "mobile", "usage_id": "intent", "more_action": "default", "sub_name": "default", "sub_q": "default", "meta": {"seed_keyword": "차이점", "domain": "", "purpose": "download_serp"}}, "information": {"version": "2.1.30.master", "displayed_query": "stir-fried", "parsed_time": "2022-05-12T01:09:14.807Z"}, "features": [{"type": "knowledge_panel", "_selector": "div:nth-child(1)#cnt > div:nth-child(8)#center_col.center_col.s6JM6d > div:nth-child(4) > div:nth-child(2)#rso > div:nth-child(1).kp-wholepage.ss6qqb.mnr-c.UBoxCb.kp-wholepage-osrp.EyBRub", "attrids": [{"attrid": "image"}, {"attrid": "secondary image"}, {"attrid": "secondary image"}, {"attrid": "secondary image"}, {"attrid": "secondary image"}, {"attrid": "secondary image"}, {"attrid": "secondary image"}, {"attrid": "secondary image"}, {"attrid": "secondary image"}, {"attrid": "secondary image"}, {"attrid": "secondary image"}, {"attrid": "description", "values": ["볶기는 불에 달군 프라이팬이나 냄비에 기름을 두르고 식품을 넣어서 가열하면 식품이 볶아지면서 익는 조리법으로, 굽기와 튀기기의 중간 방법이다. 볶는 조리법은 독특한 향기와 고소한 맛이 생기며, 지방과 지용성 비타민의 흡수가 좋아진다.", "위키백과"]}], "cards": [{"card_name": "images", "_debug_name": "small_images", "images": [{"height": "144px", "width": "150px"}, {"height": "144px", "width": "96px"}, {"height": "144px", "width": "96px"}, {"height": "144px", "width": "158px"}, {"height": "144px", "width": "96px"}, {"height": "144px", "width": "192px"}, {"height": "144px", "width": "192px"}, {"height": "144px", "width": "96px"}, {"height": "144px", "width": "192px"}, {"height": "144px", "width": "158px"}, {"height": "144px", "width": "192px"}]}, {"Description": "볶기는 불에 달군 프라이팬이나 냄비에 기름을 두르고 식품을 넣어서 가열하면 식품이 볶아지면서 익는 조리법으로, 굽기와 튀기기의 중간 방법이다. 볶는 조리법은 독특한 향기와 고소한 맛이 생기며, 지방과 지용성 비타민의 흡수가 좋아진다.  "}], "_attrids": ["image", "secondary image", "secondary image", "secondary image", "secondary image", "secondary image", "secondary image", "secondary image", "secondary image", "secondary image", "secondary image", "description"], "sequence": 1}, {"type": "knowledge_panel", "_selector": "div:nth-child(1)#cnt > div:nth-child(8)#center_col.center_col.s6JM6d > div:nth-child(4) > div:nth-child(2)#rso > div:nth-child(1).kp-wholepage.ss6qqb.mnr-c.UBoxCb.kp-wholepage-osrp.EyBRub > div:nth-child(2) > div:nth-child(2)#_Nl58Yqu1D5HO2roP2OOfMA11.osrp-blk > div:nth-child(3) > div:nth-child(1).Kot7x > div:nth-child(1)#kp-wp-tab-cont-overview > div:nth-child(1).aoPfOc > div:nth-child(1)#kp-wp-tab-overview > div:nth-child(1).TzHB6b.JlDOsc.LMRCfc.Giv2qe > div:nth-child(1) > div:nth-child(1).sATSHe > div:nth-child(1) > div:nth-child(2).LuVEUc.CGCvRb.TjcfIc.eE3xqf.B03h3d.P6OZi.V14nKc.ptcLIOszQJu__wholepage-card.wp-ms", "attrids": [{"attrid": "image"}, {"attrid": "secondary image"}, {"attrid": "secondary image"}, {"attrid": "secondary image"}, {"attrid": "secondary image"}, {"attrid": "secondary image"}, {"attrid": "secondary image"}, {"attrid": "secondary image"}, {"attrid": "secondary image"}, {"attrid": "secondary image"}, {"attrid": "secondary image"}], "cards": [{"card_name": "images", "_debug_name": "small_images", "images": [{"height": "144px", "width": "150px"}, {"height": "144px", "width": "96px"}, {"height": "144px", "width": "96px"}, {"height": "144px", "width": "158px"}, {"height": "144px", "width": "96px"}, {"height": "144px", "width": "192px"}, {"height": "144px", "width": "192px"}, {"height": "144px", "width": "96px"}, {"height": "144px", "width": "192px"}, {"height": "144px", "width": "158px"}, {"height": "144px", "width": "192px"}]}], "_attrids": ["image", "secondary image", "secondary image", "secondary image", "secondary image", "secondary image", "secondary image", "secondary image", "secondary image", "secondary image", "secondary image"], "sequence": 2}, {"type": "knowledge_panel", "_selector": "div:nth-child(1)#cnt > div:nth-child(8)#center_col.center_col.s6JM6d > div:nth-child(4) > div:nth-child(2)#rso > div:nth-child(1).kp-wholepage.ss6qqb.mnr-c.UBoxCb.kp-wholepage-osrp.EyBRub > div:nth-child(2) > div:nth-child(2)#_Nl58Yqu1D5HO2roP2OOfMA11.osrp-blk > div:nth-child(3) > div:nth-child(1).Kot7x > div:nth-child(1)#kp-wp-tab-cont-overview > div:nth-child(1).aoPfOc > div:nth-child(1)#kp-wp-tab-overview > div:nth-child(10).TzHB6b.JlDOsc.SHuCDf > div:nth-child(1) > div:nth-child(1).sATSHe > div:nth-child(1) > div:nth-child(2).LuVEUc.TjcfIc.B03h3d.P6OZi.V14nKc.ptcLIOszQJu__wholepage-card.wp-ms", "attrids": [{"attrid": "description", "values": ["볶기는 불에 달군 프라이팬이나 냄비에 기름을 두르고 식품을 넣어서 가열하면 식품이 볶아지면서 익는 조리법으로, 굽기와 튀기기의 중간 방법이다. 볶는 조리법은 독특한 향기와 고소한 맛이 생기며, 지방과 지용성 비타민의 흡수가 좋아진다.", "위키백과"]}], "cards": [{"Description": "볶기는 불에 달군 프라이팬이나 냄비에 기름을 두르고 식품을 넣어서 가열하면 식품이 볶아지면서 익는 조리법으로, 굽기와 튀기기의 중간 방법이다. 볶는 조리법은 독특한 향기와 고소한 맛이 생기며, 지방과 지용성 비타민의 흡수가 좋아진다.  "}], "_attrids": ["description"], "sequence": 3}, {"type": "organic_results", "_selector": "div:nth-child(1)#cnt > div:nth-child(8)#center_col.center_col.s6JM6d > div:nth-child(4) > div:nth-child(2)#rso > div:nth-child(7) > div:nth-child(1).mnr-c.xpd.O9g5cc.uUPGi > div:nth-child(1).jtfYYd > div:nth-child(1).NJo7tc.Z26q7c > div:nth-child(1) > div:nth-child(1).mnr-c.xpd.O9g5cc.uUPGi", "position": 1, "displayed_link": "https://dictionary.cambridge.org › st...", "title": "영어로 stir-fried의 뜻", "url": "https://dictionary.cambridge.org/ko/%EC%82%AC%EC%A0%84/%EC%98%81%EC%96%B4/stir-fried", "snippet": "2022. 4. 27. — stir-fried 의미, 정의, stir-fried의 정의: 1. past participle, past simple of stir-fry 2. to fry small pieces of meat, vegetables, etc…", "sequence": 4}, {"type": "organic_results", "_selector": "div:nth-child(1)#cnt > div:nth-child(8)#center_col.center_col.s6JM6d > div:nth-child(4) > div:nth-child(2)#rso > div:nth-child(7) > div:nth-child(1).mnr-c.xpd.O9g5cc.uUPGi > div:nth-child(1).jtfYYd > div:nth-child(3).NJo7tc.Z26q7c > div:nth-child(1) > div:nth-child(1).mnr-c.xpd.O9g5cc.uUPGi", "position": 2, "displayed_link": "https://dictionary.cambridge.org › st...", "title": "영어로 stir-fry의 뜻", "url": "https://dictionary.cambridge.org/ko/%EC%82%AC%EC%A0%84/%EC%98%81%EC%96%B4/stir-fry", "snippet": "8일 전 — stir-fry 의미, 정의, stir-fry의 정의: 1. to fry small pieces of meat, vegetables, etc. quickly while mixing them around: 2. a method of…", "sequence": 5}, {"type": "people_also_search_for", "_selector": "div:nth-child(1)#cnt > div:nth-child(8)#center_col.center_col.s6JM6d > div:nth-child(4) > div:nth-child(2)#rso > div:nth-child(8).AuVD.wHYlTd.mnr-c", "searches": [{"query": "stir-fried 뜻", "_selector": "div:nth-child(1)#cnt > div:nth-child(8)#center_col.center_col.s6JM6d > div:nth-child(4) > div:nth-child(2)#rso > div:nth-child(8).AuVD.wHYlTd.mnr-c > div:nth-child(2).ouy7Mc > div:nth-child(2) > div:nth-child(2)#TEXT_REFINEMENT_33_Nl58Yqu1D5HO2roP2OOfMA__34 > div:nth-child(1) > a.iOJVmb > div:nth-child(2).gbCQS.u60jwe.gduDCb > div:nth-child(1).gkd1F.VlWUDb.RrotFd > span.RrotFd.wHYlTd"}, {"query": "Stir-fried noodles", "_selector": "div:nth-child(1)#cnt > div:nth-child(8)#center_col.center_col.s6JM6d > div:nth-child(4) > div:nth-child(2)#rso > div:nth-child(8).AuVD.wHYlTd.mnr-c > div:nth-child(2).ouy7Mc > div:nth-child(3) > div:nth-child(2)#TEXT_REFINEMENT_34_Nl58Yqu1D5HO2roP2OOfMA__35 > div:nth-child(1) > a.iOJVmb > div:nth-child(2).gbCQS.u60jwe.gduDCb > div:nth-child(1).gkd1F.VlWUDb.RrotFd > span.RrotFd.wHYlTd"}, {"query": "Stir fry", "_selector": "div:nth-child(1)#cnt > div:nth-child(8)#center_col.center_col.s6JM6d > div:nth-child(4) > div:nth-child(2)#rso > div:nth-child(8).AuVD.wHYlTd.mnr-c > div:nth-child(2).ouy7Mc > div:nth-child(4) > div:nth-child(2)#TEXT_REFINEMENT_35_Nl58Yqu1D5HO2roP2OOfMA__36 > div:nth-child(1) > a.iOJVmb > div:nth-child(2).gbCQS.u60jwe.gduDCb > div:nth-child(1).gkd1F.VlWUDb.RrotFd > span.RrotFd.wHYlTd"}, {"query": "Stir fried shrimp", "_selector": "div:nth-child(1)#cnt > div:nth-child(8)#center_col.center_col.s6JM6d > div:nth-child(4) > div:nth-child(2)#rso > div:nth-child(8).AuVD.wHYlTd.mnr-c > div:nth-child(2).ouy7Mc > div:nth-child(5) > div:nth-child(2)#TEXT_REFINEMENT_36_Nl58Yqu1D5HO2roP2OOfMA__37 > div:nth-child(1) > a.iOJVmb > div:nth-child(2).gbCQS.u60jwe.gduDCb > div:nth-child(1).gkd1F.VlWUDb.RrotFd > span.RrotFd.wHYlTd"}, {"query": "Stir fry vegetables", "_selector": "div:nth-child(1)#cnt > div:nth-child(8)#center_col.center_col.s6JM6d > div:nth-child(4) > div:nth-child(2)#rso > div:nth-child(8).AuVD.wHYlTd.mnr-c > div:nth-child(2).ouy7Mc > div:nth-child(6) > div:nth-child(2)#TEXT_REFINEMENT_37_Nl58Yqu1D5HO2roP2OOfMA__39 > div:nth-child(1) > a.iOJVmb > div:nth-child(2).gbCQS.u60jwe.gduDCb > div:nth-child(1).gkd1F.VlWUDb.RrotFd > span.RrotFd.wHYlTd"}, {"query": "Cooking", "_selector": "div:nth-child(1)#cnt > div:nth-child(8)#center_col.center_col.s6JM6d > div:nth-child(4) > div:nth-child(2)#rso > div:nth-child(8).AuVD.wHYlTd.mnr-c > div:nth-child(2).ouy7Mc > div:nth-child(7) > div:nth-child(2)#TEXT_REFINEMENT_38_Nl58Yqu1D5HO2roP2OOfMA__40 > div:nth-child(1) > a.iOJVmb > div:nth-child(2).gbCQS.u60jwe.gduDCb > div:nth-child(1).gkd1F.VlWUDb.RrotFd > span.RrotFd.wHYlTd"}], "sequence": 6}, {"type": "organic_results", "_selector": "div:nth-child(1)#cnt > div:nth-child(8)#center_col.center_col.s6JM6d > div:nth-child(4) > div:nth-child(2)#rso > div:nth-child(9) > div:nth-child(1).mnr-c.xpd.O9g5cc.uUPGi", "position": 3, "displayed_link": "https://en.m.wikipedia.org › wiki", "title": "Stir frying - Wikipedia", "url": "https://en.m.wikipedia.org/wiki/Stir_frying", "snippet": "Stir frying (Chinese: 炒; pinyin: chǎo) is a Chinese cooking technique in which ingredients are fried in a small amount of very hot oil while being stirred ...", "thumbnail": {"type": "image", "url": "https://en.m.wikipedia.org/wiki/Stir_frying"}, "sequence": 7}, {"type": "organic_results", "_selector": "div:nth-child(1)#cnt > div:nth-child(8)#center_col.center_col.s6JM6d > div:nth-child(4) > div:nth-child(2)#rso > div:nth-child(10) > div:nth-child(1).mnr-c.xpd.O9g5cc.uUPGi", "position": 4, "displayed_link": "https://therecipecritic.com › vegetabl...", "title": "Easiest Vegetable Stir Fry | The Recipe Critic", "url": "https://therecipecritic.com/vegetable-stir-fry/", "snippet": "2019. 9. 1. — Stir frying is a Chinese cooking technique in which ingredients are fried in a small amount of very hot oil while being stirred in a wok. The ...", "thumbnail": {"type": "video", "url": "https://therecipecritic.com/vegetable-stir-fry/", "desc": "stir-fried 동영상"}, "rating": {"rating_count": "(45)", "rating_value": "4.9"}, "sequence": 8}, {"type": "organic_results", "_selector": "div:nth-child(1)#cnt > div:nth-child(8)#center_col.center_col.s6JM6d > div:nth-child(4) > div:nth-child(2)#rso > div:nth-child(11) > div:nth-child(1).mnr-c.xpd.O9g5cc.uUPGi", "position": 5, "displayed_link": "https://www.ldoceonline.com › stir-fry", "title": "stir-fry | Longman Dictionary of Contemporary English에서 stir-fry의 어의 | LDOCE", "url": "https://www.ldoceonline.com/ko/dictionary/stir-fry", "snippet": "stir-fry 어의, 의미, stir-fry의 의미: to cook small pieces of food quickly by ...: 자세히 알아보기.", "sequence": 9}, {"type": "video_results", "_selector": "div:nth-child(1)#cnt > div:nth-child(8)#center_col.center_col.s6JM6d > div:nth-child(4) > div:nth-child(2)#rso > div:nth-child(12).uVMCKf.mnr-c > div:nth-child(5)", "title": "VideosView All", "videos": [{"title": "How to Stir-Fry", "url": "https://m.youtube.com/watch?v=8bEBVO1jiXU"}, {"title": "Korean Spicy Stir-fried Noodles", "url": "https://www.youtube.com/watch?v=_Tr6DD2Ncp8&vl=ko"}, {"title": "상큼한 토마토와 계란의 만남, 토마토 계란볶음 / Stir-fried tomato eggs", "url": "https://m.youtube.com/watch?v=1AntGZ5mlig"}, {"title": "집밥 먹방 :) 밥도둑 조기조림에 밤 듬뿍 돌솥밥, 쏘야, 오징어실채볶음, 방풍나물. 후식은 달달한 수박.", "url": "https://www.youtube.com/watch?v=reXqLlFYI1o&vl=ko"}], "sequence": 10}, {"type": "organic_results", "_selector": "div:nth-child(1)#cnt > div:nth-child(8)#center_col.center_col.s6JM6d > div:nth-child(4) > div:nth-child(2)#rso > div:nth-child(13) > div:nth-child(1).mnr-c.xpd.O9g5cc.uUPGi", "position": 6, "url": "https://haemukja.com/m/recipes/2899", "thumbnail": {"type": "image"}, "sequence": 11}, {"type": "organic_results", "_selector": "div:nth-child(1)#cnt > div:nth-child(8)#center_col.center_col.s6JM6d > div:nth-child(4) > div:nth-child(2)#rso > div:nth-child(14) > div:nth-child(1).mnr-c.xpd.O9g5cc.uUPGi > div:nth-child(1).jtfYYd > div:nth-child(1).NJo7tc.Z26q7c > div:nth-child(1) > div:nth-child(1).mnr-c.xpd.O9g5cc.uUPGi", "position": 7, "displayed_link": "https://www.collinsdictionary.com › ...", "title": "Stir-fried definition and meaning | Collins English Dictionary", "url": "https://www.collinsdictionary.com/ko/dictionary/english/stir-fried", "snippet": "Stir-fried definition: to cook (small pieces of meat , vegetables , etc) rapidly by stirring them in a wok or... | Meaning, pronunciation, translations and ...", "sequence": 12}, {"type": "organic_results", "_selector": "div:nth-child(1)#cnt > div:nth-child(8)#center_col.center_col.s6JM6d > div:nth-child(4) > div:nth-child(2)#rso > div:nth-child(14) > div:nth-child(1).mnr-c.xpd.O9g5cc.uUPGi > div:nth-child(1).jtfYYd > div:nth-child(3).NJo7tc.Z26q7c > div:nth-child(1) > div:nth-child(1).mnr-c.xpd.O9g5cc.uUPGi", "position": 8, "displayed_link": "https://www.collinsdictionary.com › ...", "title": "Stir-fry definition and meaning | Collins English Dictionary", "url": "https://www.collinsdictionary.com/ko/dictionary/english/stir-fry", "snippet": "2022. 5. 3. — Stir-fry definition: If you stir-fry vegetables, meat, or fish , you cook small pieces of them quickly by... | Meaning, pronunciation ...", "sequence": 13}, {"type": "organic_results", "_selector": "div:nth-child(1)#cnt > div:nth-child(8)#center_col.center_col.s6JM6d > div:nth-child(4) > div:nth-child(2)#rso > div:nth-child(15) > div:nth-child(1).mnr-c.xpd.O9g5cc.uUPGi", "position": 9, "displayed_link": "http://ko.wordow.com › dictionary", "title": "stir-fried 뜻 - 영어 사전", "url": "http://ko.amp.wordow.com/english/dictionary/stir-fried", "snippet": "에서 한국어 내부, 우리는 어떻게 설명 할stir-fried영어 단어 그것은? stir-fried영어 단어는 다음과 같은 의미를 한국어 :- 볶음, 볶음. Meaning of stir-fried for ...", "sequence": 14}, {"type": "organic_results", "_selector": "div:nth-child(1)#cnt > div:nth-child(8)#center_col.center_col.s6JM6d > div:nth-child(4) > div:nth-child(2)#rso > div:nth-child(16) > div:nth-child(1).mnr-c.xpd.O9g5cc.uUPGi", "position": 10, "displayed_link": "https://surestepup.tistory.com › ...", "title": "stir-fry 뜻은? 요리 영어단어표현 총 정리", "url": "https://surestepup.tistory.com/m/46", "snippet": "2020. 7. 6. — stir-fry는 무슨 뜻일까요? 알고 보면 우리가 많이 쓰는 요리 용어들,. 영어로는 어떤 것이 있는지 알아 보아요 :) ...", "sequence": 15}, {"type": "organic_results", "_selector": "div:nth-child(1)#cnt > div:nth-child(8)#center_col.center_col.s6JM6d > div:nth-child(4) > div:nth-child(2)#rso > div:nth-child(17) > div:nth-child(1).mnr-c.xpd.O9g5cc.uUPGi > div:nth-child(1).jtfYYd > div:nth-child(1).NJo7tc.Z26q7c > div:nth-child(1) > div:nth-child(1).mnr-c.xpd.O9g5cc.uUPGi", "position": 11, "displayed_link": "https://www.bbcgoodfood.com › stir...", "title": "Stir-fry recipes | BBC Good Food", "url": "https://www.bbcgoodfood.com/recipes/collection/stir-fry-recipes/amp", "snippet": "Items 1 - 22 of 81 — Use our fragrant stir-fry recipes to whip up a speedy midweek meal. Season your wok with Singapore noodles, chicken chow mein, fried rice, ...", "thumbnail": {"type": "image", "url": "https://www.bbcgoodfood.com/recipes/collection/stir-fry-recipes/amp", "desc": "stir-fried(출처: www.bbcgoodfood.com)"}, "sequence": 16}, {"type": "organic_results", "_selector": "div:nth-child(1)#cnt > div:nth-child(8)#center_col.center_col.s6JM6d > div:nth-child(4) > div:nth-child(2)#rso > div:nth-child(17) > div:nth-child(1).mnr-c.xpd.O9g5cc.uUPGi > div:nth-child(1).jtfYYd > div:nth-child(3).NJo7tc.Z26q7c > div:nth-child(1) > div:nth-child(1).mnr-c.xpd.O9g5cc.uUPGi", "position": 12, "displayed_link": "https://www.bbcgoodfood.com › si...", "title": "Simple stir-fry recipe | BBC Good Food", "url": "https://www.bbcgoodfood.com/recipes/simple-stir-fry/amp", "snippet": "2021. 12. 16. — Ingredients · 500g vegetables such as carrots, baby corn, broccoli, courgettes, red peppers and cabbage or pak choi · 1 tbsp rapeseed oil · 1 ...", "thumbnail": {"type": "image", "url": "https://www.bbcgoodfood.com/recipes/simple-stir-fry/amp", "desc": "stir-fried(출처: www.bbcgoodfood.com)"}, "rating": {"rating_count": "(12)", "rating_value": "5.0"}, "sequence": 17}, {"type": "organic_results", "_selector": "div:nth-child(1)#cnt > div:nth-child(8)#center_col.center_col.s6JM6d > div:nth-child(4) > div:nth-child(2)#rso > div:nth-child(18) > div:nth-child(1).mnr-c.xpd.O9g5cc.uUPGi", "position": 13, "displayed_link": "https://www.dictionary.com › browse", "title": "Stir-fried Definition & Meaning | Dictionary.com", "url": "https://www.dictionary.com/browse/stir-fried", "snippet": "Stir-fried definition, (of food) prepared by cooking quickly in a small amount of oil over high heat: stir-fried shrimp and snow peas. See more.", "sequence": 18}, {"type": "organic_results", "_selector": "div:nth-child(1)#cnt > div:nth-child(8)#center_col.center_col.s6JM6d > div:nth-child(4) > div:nth-child(2)#rso > div:nth-child(19) > div:nth-child(1).mnr-c.xpd.O9g5cc.uUPGi", "position": 14, "displayed_link": "https://www.bbc.co.uk › recipes › sa...", "title": "Easy vegetable stir-fry recipe - BBC Food", "url": "https://www.bbc.co.uk/food/recipes/sachas_stir-fry_17077/amp", "snippet": "Method · Heat a wok on a high heat and add the sunflower oil. · Add the carrot, red pepper and baby sweetcorn and stir-fry for 2 minutes. · Add 1 tablespoon water, ...", "thumbnail": {"type": "image", "url": "https://www.bbc.co.uk/food/recipes/sachas_stir-fry_17077/amp", "desc": "stir-fried(출처: www.bbc.co.uk)"}, "rating": {"rating_count": "(24)", "rating_value": "4.7"}, "sequence": 19}, {"type": "organic_results", "_selector": "div:nth-child(1)#cnt > div:nth-child(8)#center_col.center_col.s6JM6d > div:nth-child(4) > div:nth-child(2)#rso > div:nth-child(20) > div:nth-child(1).mnr-c.xpd.O9g5cc.uUPGi", "position": 15, "displayed_link": "https://tr-ex.me › 번역 › stir+fry", "title": "STIR FRY - 한국어 뜻 - 한국어 번역 - Tr-ex", "url": "https://tr-ex.me/%EB%B2%88%EC%97%AD/%EC%98%81%EC%96%B4-%ED%95%9C%EA%B5%AD%EC%96%B4/stir+fry", "snippet": "In a stir fry you start out cooking everything in very high heat until its 2/3 the way cooked then add a sauce wine vinegar broth or water and simmer until ...", "sequence": 20}, {"type": "organic_results", "_selector": "div:nth-child(1)#cnt > div:nth-child(8)#center_col.center_col.s6JM6d > div:nth-child(4) > div:nth-child(2)#rso > div:nth-child(21) > div:nth-child(1).mnr-c.xpd.O9g5cc.uUPGi", "position": 16, "displayed_link": "https://www.justonecookbook.com › ...", "title": "Stir-Fried Vegetables (Yasai Itame) (Video) 野菜炒め - Just One Cookbook", "url": "https://www.justonecookbook.com/stir-fry-vegetables/", "snippet": "Many Japanese home cooks also use a frying pan to cook Yasai Itame. This recipe when cooked on a standard stove may not taste the same as a stir fry vegetable ...", "thumbnail": {"type": "video", "url": "https://www.justonecookbook.com/stir-fry-vegetables/", "desc": "stir-fried 동영상"}, "rating": {"rating_count": "(68)", "rating_value": "4.6"}, "sequence": 21}, {"type": "organic_results", "_selector": "div:nth-child(1)#cnt > div:nth-child(8)#center_col.center_col.s6JM6d > div:nth-child(4) > div:nth-child(2)#rso > div:nth-child(22) > div:nth-child(1).mnr-c.xpd.O9g5cc.uUPGi", "position": 17, "displayed_link": "https://www.allrecipes.com › ... › Beef", "title": "Quick Beef Stir-Fry Recipe | Allrecipes", "url": "https://www.allrecipes.com/recipe/228823/quick-beef-stir-fry/", "snippet": "Heat vegetable oil in a large wok or skillet over medium-high heat; cook and stir beef until browned, 3 to 4 minutes. Move beef to the side of the wok and add ...", "thumbnail": {"type": "video", "url": "https://www.allrecipes.com/recipe/228823/quick-beef-stir-fry/", "desc": "stir-fried 동영상"}, "rating": {"rating_count": "(364)", "rating_value": "4.4"}, "sequence": 22}, {"type": "organic_results", "_selector": "div:nth-child(1)#cnt > div:nth-child(8)#center_col.center_col.s6JM6d > div:nth-child(4) > div:nth-child(2)#rso > div:nth-child(23) > div:nth-child(1).mnr-c.xpd.O9g5cc.uUPGi", "position": 18, "displayed_link": "https://www.budgetbytes.com › easy...", "title": "Easy Vegetable Stir Fry - Budget Bytes", "url": "https://www.budgetbytes.com/easy-vegetable-stir-fry/", "snippet": "2022. 3. 15. — Make the stir fry sauce first. · Chop the vegetables into similar-sized pieces. · Add the cooking oil to a very large skillet or wok. · Next, add ...", "thumbnail": {"type": "image", "url": "https://www.budgetbytes.com/easy-vegetable-stir-fry/", "desc": "stir-fried(출처: www.budgetbytes.com)"}, "rating": {"rating_count": "(6)", "rating_value": "5.0"}, "sequence": 23}, {"type": "organic_results", "_selector": "div:nth-child(1)#cnt > div:nth-child(8)#center_col.center_col.s6JM6d > div:nth-child(4) > div:nth-child(2)#rso > div:nth-child(24) > div:nth-child(1).mnr-c.xpd.O9g5cc.uUPGi", "position": 19, "displayed_link": "https://www.foodnetwork.com › ho...", "title": "How to Stir-Fry: A Step-by-Step Guide - Food Network", "url": "https://www.foodnetwork.com/how-to/articles/how-to-stir-fry-a-step-by-step-guide", "snippet": "A wok is best for stir-fries because its shape keeps the food moving. Put it over super-high heat, add the oil and then add aromatics like garlic and ginger.", "thumbnail": {"type": "image", "url": "https://www.foodnetwork.com/how-to/articles/how-to-stir-fry-a-step-by-step-guide", "desc": "stir-fried(출처: www.foodnetwork.com)"}, "sequence": 24}, {"type": "related_searches", "_selector": "div:nth-child(1)#cnt > div:nth-child(8)#center_col.center_col.s6JM6d > div:nth-child(6)#botstuff > div:nth-child(1) > div:nth-child(1)#bres > div:nth-child(1).AuVD.wHYlTd.mnr-c", "results": [{"query": "Stir 뜻", "_selector": "div:nth-child(1)#cnt > div:nth-child(8)#center_col.center_col.s6JM6d > div:nth-child(6)#botstuff > div:nth-child(1) > div:nth-child(1)#bres > div:nth-child(1).AuVD.wHYlTd.mnr-c > div:nth-child(1).ouy7Mc > div:nth-child(2) > div:nth-child(1)#TEXT_REFINEMENT_91_Nl58Yqu1D5HO2roP2OOfMA__38 > div:nth-child(1) > a.iOJVmb"}, {"query": "Sautéed", "_selector": "div:nth-child(1)#cnt > div:nth-child(8)#center_col.center_col.s6JM6d > div:nth-child(6)#botstuff > div:nth-child(1) > div:nth-child(1)#bres > div:nth-child(1).AuVD.wHYlTd.mnr-c > div:nth-child(1).ouy7Mc > div:nth-child(3) > div:nth-child(2)#TEXT_REFINEMENT_92_Nl58Yqu1D5HO2roP2OOfMA__41 > div:nth-child(1) > a.iOJVmb"}, {"query": "볶음 meaning", "_selector": "div:nth-child(1)#cnt > div:nth-child(8)#center_col.center_col.s6JM6d > div:nth-child(6)#botstuff > div:nth-child(1) > div:nth-child(1)#bres > div:nth-child(1).AuVD.wHYlTd.mnr-c > div:nth-child(1).ouy7Mc > div:nth-child(4) > div:nth-child(2)#TEXT_REFINEMENT_93_Nl58Yqu1D5HO2roP2OOfMA__42 > div:nth-child(1) > a.iOJVmb"}, {"query": "Sautéing", "_selector": "div:nth-child(1)#cnt > div:nth-child(8)#center_col.center_col.s6JM6d > div:nth-child(6)#botstuff > div:nth-child(1) > div:nth-child(1)#bres > div:nth-child(1).AuVD.wHYlTd.mnr-c > div:nth-child(1).ouy7Mc > div:nth-child(5) > div:nth-child(2)#TEXT_REFINEMENT_94_Nl58Yqu1D5HO2roP2OOfMA__43 > div:nth-child(1) > a.iOJVmb"}, {"query": "Chow mein", "_selector": "div:nth-child(1)#cnt > div:nth-child(8)#center_col.center_col.s6JM6d > div:nth-child(6)#botstuff > div:nth-child(1) > div:nth-child(1)#bres > div:nth-child(1).AuVD.wHYlTd.mnr-c > div:nth-child(1).ouy7Mc > div:nth-child(6) > div:nth-child(2)#TEXT_REFINEMENT_95_Nl58Yqu1D5HO2roP2OOfMA__44 > div:nth-child(1) > a.iOJVmb"}, {"query": "Gentle frying", "_selector": "div:nth-child(1)#cnt > div:nth-child(8)#center_col.center_col.s6JM6d > div:nth-child(6)#botstuff > div:nth-child(1) > div:nth-child(1)#bres > div:nth-child(1).AuVD.wHYlTd.mnr-c > div:nth-child(1).ouy7Mc > div:nth-child(7) > div:nth-child(2)#TEXT_REFINEMENT_96_Nl58Yqu1D5HO2roP2OOfMA__45 > div:nth-child(1) > a.iOJVmb"}, {"query": "Water spinach", "_selector": "div:nth-child(1)#cnt > div:nth-child(8)#center_col.center_col.s6JM6d > div:nth-child(6)#botstuff > div:nth-child(1) > div:nth-child(1)#bres > div:nth-child(1).AuVD.wHYlTd.mnr-c > div:nth-child(1).ouy7Mc > div:nth-child(8) > div:nth-child(2)#TEXT_REFINEMENT_97_Nl58Yqu1D5HO2roP2OOfMA__46 > div:nth-child(1) > a.iOJVmb"}, {"query": "Baby corn", "_selector": "div:nth-child(1)#cnt > div:nth-child(8)#center_col.center_col.s6JM6d > div:nth-child(6)#botstuff > div:nth-child(1) > div:nth-child(1)#bres > div:nth-child(1).AuVD.wHYlTd.mnr-c > div:nth-child(1).ouy7Mc > div:nth-child(9) > div:nth-child(2)#TEXT_REFINEMENT_98_Nl58Yqu1D5HO2roP2OOfMA__47 > div:nth-child(1) > a.iOJVmb"}], "sequence": 25}]}