{"search_parameters": {"engine": "google", "id": "64ab3304-b0b7-4b1a-bc3a-e5307da3b537", "sub_id": 0, "requested_time": "2023-11-14T01:28:50.022Z", "q": "탐침 뜻", "location": "South Korea", "gl": "kr", "hl": "ko", "num": 20, "query_string": "sourceid=chrome&ie=UTF-8&q=%ED%83%90%EC%B9%A8+%EB%9C%BB&hl=ko&gl=kr&uule=w+CAIQICILU291dGggS29yZWE&num=20", "html_url": "http://node0027.k8s.prod.ascentlab.io:8080/serpapi/serpdata/intent/231114/2311141028/GG%09M%09ko%09kr%090cea29dc7497cfce53bd49303e9acae80004%09South%20Korea%0920231114012850022.html", "json_url": "http://node0027.k8s.prod.ascentlab.io:8080/serpapi/serpdata/intent/231114/2311141028/GG%09M%09ko%09kr%090cea29dc7497cfce53bd49303e9acae80004%09South%20Korea%0920231114012850022.json", "crawl_start_time": "2023-11-14T01:28:50.702Z", "crawl_end_time": "2023-11-14T01:28:56.496Z", "device": "mobile", "usage_id": "intent", "sub_name": "default", "sub_q": "default", "meta": {"seed_keyword": "자전거용품", "domain": "wp", "purpose": "download_serp"}, "crawl_elapsed_time": 5.79}, "information": {"version": "5.12.0.master", "displayed_query": "탐침 뜻", "parsed_time": "2023-11-14T01:28:57.170Z"}, "features": [{"sequence": 1, "type": "featured_snippet", "results": [{"title": "[용어 아하!] 프로브(Probe) - [디지털타임스]", "displayed_link": "http://m.dt.co.kr › contents", "url": "http://m.dt.co.kr/contents.html?article_no=2013012202012269785001", "snippet": "프로브란 진공관 전압계(VTVM)나 오실로스코프 등 입력 단자에 접속해서 피측정점에 접촉시키기 위해 사용하는 것을 뜻하며 `탐침'이라고 부르기도 합니다.", "emphasis": ["진공관 전압계(VTVM)나 오실로스코프 등 입력 단자에 접속해서 피측정점에 접촉시키기 위해 사용하는 것을 뜻하며 `탐침'이라고 부르기도 합니다"]}], "official": true}, {"sequence": 2, "type": "organic_results", "position": 1, "site_name": "wordrow.kr", "displayed_link": "https://wordrow.kr › 사전", "title": "탐침 뜻: 지뢰 따위가 있는지 알아내려고 찔러 보는 기구., 곤충의 작고 뾰족한 강모(剛毛) 같은 ...", "url": "https://wordrow.kr/%EC%9D%98%EB%AF%B8/%ED%83%90%EC%B9%A8/amp/", "snippet": "▹ 탐침의 의미. 1 탐침 探針 : 지뢰 따위가 있는지 알아내려고 찔러 보는 기구. 2 탐침 探針 : 곤충의 작고 뾰족한 강모(剛毛) 같은 부속 기관."}, {"sequence": 3, "type": "organic_results", "position": 2, "site_name": "wordrow.kr", "displayed_link": "https://wordrow.kr › 사전", "title": "탐침 뜻: 지뢰 따위가 있는지 알아내려고 찔러 보는 기구.", "url": "https://wordrow.kr/%EC%9E%90%EC%84%B8%ED%95%9C-%EC%9D%98%EB%AF%B8/%ED%83%90%EC%B9%A8/1/amp/", "snippet": "탐침: 지뢰 따위가 있는지 알아내려고 찔러 보는 기구. (어휘 명사 한자어 )"}, {"sequence": 4, "type": "organic_results", "position": 3, "site_name": "네이버 블로그", "displayed_link": "https://m.blog.naver.com › dsjang6...", "date": "2019. 5. 15.", "title": "프로브(Probe, 조사, 수사, 탐사, 탐침, 검출)란?", "url": "https://m.blog.naver.com/dsjang650628/221537933054", "snippet": "2019. 5. 15. — 프로브(Probe)란 진공관 전압계(VTVM)나 오실로스코프 등 입력 단자에 접속해서 피측정점에 접촉시키기 위해 사용하는 것을 뜻하며 `탐침'이라고 부르기도 ..."}, {"sequence": 5, "type": "organic_results", "position": 4, "site_name": "Educalingo", "displayed_link": "https://educalingo.com › dic-ko › c...", "title": "한국어 사전에서 \"치과용탐침\" 뜻", "url": "https://educalingo.com/ko/dic-ko/chigwayongtamchim/amp", "snippet": "피에르 포샤르. 있다. 눈이 달려 치아, 치조, 잇몸병에 쓰는 기구 3종 그림 1. 은제 탐침. 한쪽 끝에 날 다른 쪽 모양, 날은 단추 한쪽 그림 2. 곡선형 가위. 은 뾰족하다."}, {"sequence": 6, "type": "images", "grid": {"items": [[{"source": "WORDROW", "landing_url": "https://wordrow.kr/%EC%9D%98%EB%AF%B8/%ED%83%90%EC%B9%A8/"}, {"source": "WORDROW", "landing_url": "https://wordrow.kr/%EC%9E%90%EC%84%B8%ED%95%9C-%EC%9D%98%EB%AF%B8/%ED%83%90%EC%B9%A8/1/"}], [{"source": "WORDROW", "landing_url": "https://wordrow.kr/%EC%9D%98%EB%AF%B8/%ED%83%90%EC%B9%A8%EA%B8%B0/"}, {"source": "조선계기사", "landing_url": "https://www.chosunshop.co.kr/goods/view?no=2250"}]]}}, {"sequence": 7, "type": "people_also_search_for", "searches": [{"query": "DNA probe 뜻"}, {"query": "프로브 사용법"}, {"query": "탐침 Probe"}, {"query": "프로브 종류"}, {"query": "센서 프로브"}, {"query": "DNA 탐침"}]}, {"sequence": 8, "type": "organic_results", "position": 5, "site_name": "Steemit", "displayed_link": "https://steemit.com › kr-agriculture", "title": "[재배학 해설] 유전자조작 - 5. 원하는 DNA를 찾아주는 프로브(probe, 탐침)", "url": "https://steemit.com/kr-agriculture/@stans/5-dna-probe", "snippet": "찾고자 하는 DNA에 상보적인 이중결합을 할 수 있는 한 가닥의 DNA 조각에 빛을 내는 물질을 붙여서 만든 probe입니다. 방사능을 가하면 빛이 나거나 특정 빛에 형광반응을 ..."}, {"sequence": 9, "type": "organic_results", "position": 6, "site_name": "나무위키", "displayed_link": "https://namu.wiki › 프로브", "date": "2023. 6. 16.", "title": "프로브", "url": "https://namu.wiki/w/%ED%94%84%EB%A1%9C%EB%B8%8C", "snippet": "2023. 6. 16. — 1. 단어[편집]. Probe 탐사선, 탐사기 등등을 뜻하는 단어. 1.1. 우주 탐사선[편집]. 보통 이쪽은 Space probe 라고 한다. 상세 내용 아이콘.svg 자세한 ..."}, {"sequence": 10, "type": "organic_results", "position": 7, "site_name": "한국생물공학회", "displayed_link": "https://www.ksbb.or.kr › word_view", "title": "DNA 검색 용도로 사용되는, 서열이 이미 알려진 짧은 길이의 DNA 조각. 검출이 용이하도록 표지 인자가 결합되어 있어 특정 유전자의 탐색이나 재조합 벡터의 스크리닝 등에 사용된다.", "url": "https://www.ksbb.or.kr/md_word/word_view.html?num=1466", "snippet": "DNA탐침 · DNA probe · DNA 검색 용도로 사용되는, 서열이 이미 알려진 짧은 길이의 DNA 조각. 검출이 용이하도록 표지 인자가 결합되어 있어 특정 유전자의 탐색이나 재조합 ..."}, {"sequence": 11, "type": "organic_results", "position": 8, "site_name": "Wikipedia", "displayed_link": "https://ko.m.wikipedia.org › wiki", "title": "유전자 스크리닝 - 위키백과, 우리 모두의 백과사전", "url": "https://ko.m.wikipedia.org/wiki/%EC%9C%A0%EC%A0%84%EC%9E%90_%EC%8A%A4%ED%81%AC%EB%A6%AC%EB%8B%9D", "snippet": "탐침은 목적 유전자와 최소한의 상보성을 가져야 하기 때문에 목적 유전자의 염기서열 정보가 없을 경우 혼성화에 의한 스크리닝 방법을 사용할 수 없다. 항체를 이용한 ..."}, {"sequence": 12, "type": "organic_results", "position": 9, "site_name": "플라즈마 응용연구실", "displayed_link": "http://pal.snu.ac.kr › ...", "title": "Q & A - 탐침법", "url": "http://pal.snu.ac.kr/index.php?mid=board_qna_new&document_srl=55106", "snippet": "탐침법은 탐침에서 얻어지는 전류-전압곡선을 분석하여 플라즈마의 인자들을 관찰하는 방법입니다. 여기서 전압은 탐침에 인가되는 전압을 의미하며 전압이 인가되면 탐침 ..."}, {"sequence": 13, "type": "organic_results", "position": 10, "site_name": "Tistory", "displayed_link": "https://learnenglish.tistory.com › ...", "date": "2023. 1. 9.", "title": "Probe의 뜻 그리고 예문 14가지", "url": "https://learnenglish.tistory.com/5", "snippet": "2023. 1. 9. — 2. The police are conducting a probe into the cause of the accident. 경찰은 사고 원인을 조사하고 있다. 3. NASA is sending a probe to Mars to ..."}, {"sequence": 14, "type": "images", "grid": {"items": [[{"source": "WORDROW", "landing_url": "https://wordrow.kr/%EC%9D%98%EB%AF%B8/%EB%94%94%EC%97%94%EC%97%90%EC%9D%B4%20%ED%83%90%EC%B9%A8/"}, {"source": "Steemit", "landing_url": "https://steemit.com/kr-agriculture/@stans/5-dna-probe"}], [{"source": "조선계기사", "landing_url": "https://www.chosunshop.co.kr/goods/view?no=2207"}, {"source": "네이버블로그 - NAVER", "landing_url": "https://blog.naver.com/PostView.naver?blogId=jysbw21&logNo=222555368471&parentCategoryNo=1&categoryNo=&viewDate=&isShowPopularPosts=true&from=search"}]]}}, {"sequence": 15, "type": "organic_results", "position": 11, "site_name": "JEOL Ltd.", "displayed_link": "https://ko.jeol.com › science", "title": "오거 마이크로프로브 | 과학 기초 | 제품", "url": "https://ko.jeol.com/products/science/am.php", "snippet": "마이크로는 '아주 작은'이라는 뜻이고, 탐침의 의미는 '검사나 탐색을 위한 가느다란 도구'라는 뜻이다. 원자에서 오거 전자 방출. 물질표면의 구조해석의 핵심을 ..."}, {"sequence": 16, "type": "organic_results", "position": 12, "site_name": "Google Patents", "displayed_link": "https://patents.google.com › patent", "title": "KR20060052558A - 탐침 현미경의 탐침 끝 부분에 나노구조가 선택적으로흡착되는 방법 및 ...", "url": "https://patents.google.com/patent/KR20060052558A/ko", "snippet": "본 발명에서 나노구조란, 나노입자, 나노튜브, 나노선, 탄소나노튜브, SAM, DNA, RNA, 프로테인, 항원, 항체, Cell 등의 모든 나노 크기의 구조를 통칭하는 의미이다. 본 ..."}, {"sequence": 17, "type": "organic_results", "position": 13, "site_name": "아하영어사전", "displayed_link": "http://aha-dic.com › View", "title": "[아하사전] probe - 한글발음 [프롭], 뜻 : 탐침, 소식자, 시험, (불법 행위에 대한 입법부의) ...", "url": "http://aha-dic.com/View.asp?Word=probe", "snippet": "탐침, 소식자, 시험, (불법 행위에 대한 입법부의)조사, 공중 급유용 파이프, 자세히 살피다, 조사하다, 탐침으로(소식자로)찾다, 자세히 살피다, 조사하다. probeable ..."}, {"sequence": 18, "type": "organic_results", "position": 14, "site_name": "시보드", "displayed_link": "https://cboard.net › 탐침 뜻", "title": "탐침 뜻", "url": "https://cboard.net/s/%ED%83%90%EC%B9%A8%20%EB%9C%BB", "snippet": "주사탐침현미경(SPM). SEE 장비사관학교 (School of Equipment Engineers) Scanning Probe Microscope 교육동영상 입니다."}, {"sequence": 19, "type": "organic_results", "position": 15, "site_name": "BRIC", "displayed_link": "https://www.ibric.org › bio-news", "date": "2018. 2. 5.", "title": "생체 탐침의 고효율 형광증폭 기술 개발 | 뉴스 > Bio뉴스 > 동향", "url": "https://www.ibric.org/bric/trend/bio-news.do?mode=view&articleNo=8826429", "snippet": "2018. 2. 5. — 생체 내 약물‧단백질의 위치를 추적하는 탐침(probe)의 효율이 획기적 ... 프로브 개발을 위한 디자인 전략으로서 그 의미를 가진다. □ 연구하면서 ..."}, {"sequence": 20, "type": "organic_results", "position": 16, "site_name": "Tektronix", "displayed_link": "https://download.tek.com › d...", "title": "프로브 기초", "url": "https://download.tek.com/document/60K_6053_12.pdf", "snippet": "대역폭은 오실로스코프 또는 프로브가 작동하도록 설계된. 주파수 범위를 의미합니다. 예를 들어, 100MHz 프로브. 또는 오실로스코프는 최대 100MHz의 모든 주파수에서.", "file_format": "PDF"}, {"sequence": 21, "type": "organic_results", "position": 17, "site_name": "chosunshop.co.kr", "displayed_link": "https://chosunshop.co.kr › view", "title": "ETI 전문가용 휴대용 탐침형 적외선온도계 써마펜IR (228-065)[케이스선택](온라인 판매시 판매가 준수) - 조선계기사", "url": "https://chosunshop.co.kr/goods/view?no=1920", "snippet": "... 뜻입니다. 따라서 배송준비중으로 배송상태가 넘어간 경우 취소및 반품이 불가하므로 이점 양해 부탁드립니다. 5. 타 해외구매대행 사이트에서 주문하신 물건과 주문 ..."}, {"sequence": 22, "type": "related_searches", "results": [{"query": "네트워크 프로브"}, {"query": "오실로스코프 프로브"}, {"query": "현미경 탐침"}, {"query": "프로토스 프로브"}, {"query": "탐침 온도계"}, {"query": "스타 프로브"}]}]}